<?xml version="1.0" encoding="UTF-8"?>
<beans xmlns="http://www.springframework.org/schema/beans"
	xmlns:xsi="http://www.w3.org/2001/XMLSchema-instance"
	xsi:schemaLocation="http://www.springframework.org/schema/beans http://www.springframework.org/schema/beans/spring-beans-2.5.xsd">

	<bean
		class="org.springframework.beans.factory.config.PropertyPlaceholderConfigurer">
		<property name="systemPropertiesModeName" value="SYSTEM_PROPERTIES_MODE_OVERRIDE" />
		<property name="ignoreUnresolvablePlaceholders" value="true" />
		<property name="locations">
			<value>osgibundle:activemq.properties
			</value>
		</property>
	</bean>

	<!-- Connection Factory -->
	<bean id="jmsConnectionFactory"
		class="org.springframework.jms.connection.CachingConnectionFactory">
		<property name="targetConnectionFactory">
			<bean class="org.apache.activemq.ActiveMQConnectionFactory">
				<property name="brokerURL">
					<value>${slc.server.jms.url}</value>
				</property>
			</bean>
		</property>
	</bean>


	<!--
		<bean id="jmsTransactionManager"
		class="org.springframework.jms.connection.JmsTransactionManager">
		<property name="connectionFactory" ref="jmsConnectionFactory" />
		</bean>
	-->


	<bean id="jmsCastorMessageConverter" class="org.argeo.slc.jms.MarshallerMessageConverter">
		<property name="marshaller" ref="marshaller" />
		<property name="unmarshaller" ref="unmarshaller" />
	</bean>


</beans>