<?xml version="1.0"?>

<mapping>
	<description>Message objects XML mapping</description>

	<!-- TESTS -->
	<class
		name="org.argeo.slc.msg.test.tree.CreateTreeTestResultRequest">
		<map-to ns-uri="http://argeo.org/projects/slc/schemas"
			ns-prefix="slc" />
		<field name="treeTestResult"
			type="org.argeo.slc.core.test.tree.TreeTestResult" />
	</class>

	<class
		name="org.argeo.slc.msg.test.tree.CloseTreeTestResultRequest">
		<map-to ns-uri="http://argeo.org/projects/slc/schemas"
			ns-prefix="slc" />
		<field name="resultUuid" />
		<field name="closeDate" />
	</class>

	<class name="org.argeo.slc.msg.test.tree.ResultPartRequest">
		<map-to ns-uri="http://argeo.org/projects/slc/schemas"
			ns-prefix="slc" />
		<field name="resultUuid" />
		<field name="resultPart"
			type="org.argeo.slc.core.test.SimpleResultPart">
			<bind-xml auto-naming="deriveByClass" />
		</field>

		<field name="relatedElements" collection="map">
			<bind-xml name="element" location="related-elements">
				<class name="org.exolab.castor.mapping.MapItem">
					<map-to
						ns-uri="http://argeo.org/projects/slc/schemas" ns-prefix="slc" />
					<field name="key"
						type="org.argeo.slc.core.structure.tree.TreeSPath"
						handler="org.argeo.slc.castor.structure.tree.TreeSPathFieldHandler">
						<bind-xml name="path" node="attribute" />
					</field>
					<field name="value"
						type="org.argeo.slc.core.structure.SimpleSElement">
						<bind-xml auto-naming="deriveByClass" />
					</field>
				</class>
			</bind-xml>
		</field>
		<field name="path">
			<bind-xml auto-naming="deriveByClass" />
		</field>
		<field name="testRunDescriptor" />
	</class>


	<!-- PROCESS -->
	<class name="org.argeo.slc.msg.process.SlcExecutionStepsRequest">
		<map-to ns-uri="http://argeo.org/projects/slc/schemas"
			ns-prefix="slc" />
		<field name="slcExecutionUuid" />
		<field name="steps" collection="vector"
			type="org.argeo.slc.core.process.SlcExecutionStep">
			<bind-xml auto-naming="deriveByClass" location="steps" />
		</field>
	</class>

	<class name="org.argeo.slc.msg.process.SlcExecutionStatusRequest">
		<map-to ns-uri="http://argeo.org/projects/slc/schemas"
			ns-prefix="slc" />
		<field name="slcExecutionUuid" />
		<field name="newStatus"/>
	</class>

	<class name="org.argeo.slc.msg.process.SlcExecutionRequest">
		<map-to ns-uri="http://argeo.org/projects/slc/schemas"
			ns-prefix="slc" />
		<field name="slcExecution"
			type="org.argeo.slc.core.process.SlcExecution" />
	</class>


</mapping>