<?xml version="1.0" encoding="UTF-8"?>
<beans xmlns="http://www.springframework.org/schema/beans"
	xmlns:xsi="http://www.w3.org/2001/XMLSchema-instance" xmlns:aop="http://www.springframework.org/schema/aop"
	xmlns:context="http://www.springframework.org/schema/context"
	xsi:schemaLocation="
		http://www.springframework.org/schema/beans http://www.springframework.org/schema/beans/spring-beans-2.5.xsd 
		http://www.springframework.org/schema/aop http://www.springframework.org/schema/aop/spring-aop-2.5.xsd
		http://www.springframework.org/schema/context http://www.springframework.org/schema/context/spring-context-2.5.xsd">

	<context:component-scan
		base-package="org.argeo.slc.web.mvc, org.argeo.slc.web.mvc.process" />

	<!--  Execution  -->
	<bean name="/*Execution*.service, /*Modules*.service"
		class="org.argeo.slc.web.mvc.process.ExecutionServiceController">
		<property name="agentFactory" ref="agentFactory" />
		<property name="slcExecutionDao" ref="slcExecutionDao" />
		<property name="slcExecutionService" ref="slcExecutionService" />
		<property name="marshaller" ref="marshaller" />
		<property name="unmarshaller" ref="unmarshaller" />
		<property name="attachmentsStorage" ref="attachmentsStorage" />
	</bean>

	<!--  Events  -->
	<bean name="/*Event*.service" class="org.argeo.slc.web.mvc.EventController">
		<property name="eventListenerRegister" ref="eventListenerRegister" />
		<property name="eventListener" ref="eventListener" />
	</bean>

	<!-- Provisioning -->
	<bean name="/listModularDistributions.service"
		class="org.argeo.slc.web.mvc.provisioning.ListModularDistributions">
		<property name="modularDistributions" ref="modularDistributions" />
	</bean>

	<bean name="/installModule.service" class="org.argeo.slc.web.mvc.management.InstallModule">
		<property name="dynamicRuntime" ref="dynamicRuntime" />
	</bean>

	<bean name="/uninstallModule.service" class="org.argeo.slc.web.mvc.management.UninstallModule">
		<property name="dynamicRuntime" ref="dynamicRuntime" />
	</bean>

	<!--  All that remains -->
	<bean name="/*.service" class="org.argeo.slc.web.mvc.ServiceController">
		<constructor-arg ref="testResultDao" />
		<constructor-arg ref="testResultCollectionDao" />
		<constructor-arg ref="testManagerService" />
		<constructor-arg ref="slcAgentDescriptorDao" />
		<property name="dynamicRuntime" ref="dynamicRuntime" />
		<property name="attachmentsStorage" ref="attachmentsStorage" />
	</bean>

	<bean name="eventListenerRegister" class="org.argeo.slc.web.mvc.WebSlcEventListenerRegister"
		scope="session">
		<aop:scoped-proxy />
	</bean>

	<!-- MVC -->
	<bean id="handlerMapping"
		class="org.springframework.web.servlet.handler.BeanNameUrlHandlerMapping">
		<property name="interceptors">
			<list>
				<ref bean="osivInterceptor" />
			</list>
		</property>
	</bean>

	<bean id="viewResolver" class="org.argeo.slc.web.mvc.MarshallerViewResolver">
		<constructor-arg ref="marshaller" />
	</bean>
</beans>